django_hierarchical_address-0.2.0.dist-info/licenses/LICENSE
django_places/__init__.py
django_places/admin.py
django_places/apps.py
django_places/models.py
django_places/serializers.py
django_places/tests.py
django_places/urls.py
django_places/views.py
django_places/migrations/0001_initial.py
django_places/migrations/__init__.py
django_places/static/django_places/address_chained.js
django_hierarchical_address-0.2.0.dist-info/METADATA
django_hierarchical_address-0.2.0.dist-info/WHEEL
django_hierarchical_address-0.2.0.dist-info/top_level.txt
django_hierarchical_address-0.2.0.dist-info/RECORD
