Metadata-Version: 2.4
Name: django-hierarchical-address
Version: 0.2.0
Summary: A reusable Django app for hierarchical address fields.
Home-page: https://github.com/ashkanhasani/Django-rest-places
Author: Your Name
Author-email: your.email@example.com
License: MIT
Classifier: Framework :: Django
Classifier: Programming Language :: Python :: 3
Classifier: Operating System :: OS Independent
Requires-Python: >=3.7
License-File: LICENSE
Requires-Dist: django>=3.2
Requires-Dist: djangorestframework
Provides-Extra: test
Requires-Dist: pytest; extra == "test"
Requires-Dist: pytest-django; extra == "test"
Dynamic: author
Dynamic: classifier
Dynamic: license-file
Dynamic: requires-dist
Dynamic: summary
